.DS_Store
rootprocessing/RP_IOfilecheck.py
rootprocessing/RP_crop.py
rootprocessing/RP_distmap.py
rootprocessing/RP_distwindowrange.py
rootprocessing/RP_imagefilter.py
rootprocessing/RP_linedraw.py
rootprocessing/RP_mask.py
rootprocessing/RP_radwc.py
rootprocessing/RP_remove.py
rootprocessing/RP_rootdiameter.py
rootprocessing/RP_run.py
rootprocessing/RP_stitch.py
rootprocessing/RP_thickness.py
rootprocessing/RP_timerend.py
rootprocessing/RP_timerprogress.py
rootprocessing/RP_timerstart.py
rootprocessing/RP_userconfiganalysis.py
rootprocessing/RP_wc.py
rootprocessing/RP_windowrange.py
rootprocessing/__init__.py
rootprocessing/sampledata.py
rootprocessing-1.1.11.dist-info/DESCRIPTION.rst
rootprocessing-1.1.11.dist-info/METADATA
rootprocessing-1.1.11.dist-info/RECORD
rootprocessing-1.1.11.dist-info/WHEEL
rootprocessing-1.1.11.dist-info/metadata.json
rootprocessing-1.1.11.dist-info/top_level.txt
