Metadata-Version: 2.0
Name: rootprocessing
Version: 1.1.11
Summary: Root Processing suite for images at the ORNL CG-1D beamline
Home-page: https://github.com/kdecarlo/CG1D_rootprocessing
Author: Keita DeCarlo
Author-email: kdecarlo@princeton.edu
License: BSD
Keywords: tiff tif root processing
Platform: UNKNOWN
Classifier: Development Status :: 3 - Alpha
Classifier: Topic :: Scientific/Engineering :: Physics
Classifier: Intended Audience :: Developers
Classifier: Programming Language :: Python :: 2.7
Classifier: Programming Language :: Python :: 3.4
Classifier: Programming Language :: Python :: 3.5
Requires-Dist: numpy
Requires-Dist: pillow
Requires-Dist: scipy
